phoenix_ai_agents/__init__.py
phoenix_ai_agents/agent.py
phoenix_ai_agents/audit.py
phoenix_ai_agents/cli.py
phoenix_ai_agents/memory.py
phoenix_ai_agents/orchestrator.py
phoenix_ai_agents/services.py
phoenix_ai_agents/tools.py
phoenix_ai_agents/utils.py
phoenix_ai_agents-0.1.3.dist-info/LICENSE
phoenix_ai_agents-0.1.3.dist-info/METADATA
phoenix_ai_agents-0.1.3.dist-info/WHEEL
phoenix_ai_agents-0.1.3.dist-info/entry_points.txt
phoenix_ai_agents-0.1.3.dist-info/RECORD
